karttapullautin2tiles/__init__.py
karttapullautin2tiles/cli.py
karttapullautin2tiles/assets/local_tiles_viewer.html
karttapullautin2tiles-0.1.3.dist-info/METADATA
karttapullautin2tiles-0.1.3.dist-info/WHEEL
karttapullautin2tiles-0.1.3.dist-info/entry_points.txt
karttapullautin2tiles-0.1.3.dist-info/licenses/LICENSE
karttapullautin2tiles-0.1.3.dist-info/RECORD
