Metadata-Version: 2.4
Name: karttapullautin2tiles
Version: 0.1.3
Summary: Convert the output of karttapullautin into web mercator tiles
Project-URL: Documentation, https://karttapullautin2tiles.readthedocs.io/
Project-URL: Homepage, https://github.com/grst/karttapullautin2tiles
Project-URL: Source, https://github.com/grst/karttapullautin2tiles
Author: Gregor Sturm
Maintainer-email: Gregor Sturm <gregor@sturmcloud.org>
License: 
License-File: LICENSE
Classifier: Programming Language :: Python :: 3 :: Only
Classifier: Programming Language :: Python :: 3.10
Classifier: Programming Language :: Python :: 3.11
Classifier: Programming Language :: Python :: 3.12
Classifier: Programming Language :: Python :: 3.13
Requires-Python: >=3.10
Requires-Dist: cyclopts>=3.16.1
Requires-Dist: geopandas>=1.0.1
Requires-Dist: imagesize>=1.4.1
Requires-Dist: mercantile>=1.2.1
Requires-Dist: pillow>=11.2.1
Requires-Dist: pyproj>=3.7.1
Requires-Dist: rasterio>=1.4.3
Requires-Dist: tqdm>=4.67.1
Provides-Extra: dev
Requires-Dist: pre-commit; extra == 'dev'
Requires-Dist: twine>=4.0.2; extra == 'dev'
Provides-Extra: doc
Requires-Dist: docutils!=0.18.*,!=0.19.*,>=0.8; extra == 'doc'
Requires-Dist: ipykernel; extra == 'doc'
Requires-Dist: ipython; extra == 'doc'
Requires-Dist: myst-nb>=1.1; extra == 'doc'
Requires-Dist: pandas; extra == 'doc'
Requires-Dist: setuptools; extra == 'doc'
Requires-Dist: sphinx-autodoc-typehints; extra == 'doc'
Requires-Dist: sphinx-book-theme>=1; extra == 'doc'
Requires-Dist: sphinx-copybutton; extra == 'doc'
Requires-Dist: sphinx-tabs; extra == 'doc'
Requires-Dist: sphinx>=8.1; extra == 'doc'
Requires-Dist: sphinxcontrib-bibtex>=1; extra == 'doc'
Requires-Dist: sphinxext-opengraph; extra == 'doc'
Provides-Extra: test
Requires-Dist: coverage; extra == 'test'
Requires-Dist: pytest; extra == 'test'
